enigmatui/__init__.py
enigmatui/__main__.py
enigmatui/app.py
enigmatui/css/styles.css
enigmatui/data/__init__.py
enigmatui/data/enigma_config.py
enigmatui/screens/__init__.py
enigmatui/screens/config_not_complete_modal.py
enigmatui/screens/config_null_modal.py
enigmatui/screens/configure.py
enigmatui/screens/encrypt.py
enigmatui/screens/exit_configutation_without_saving_modal.py
enigmatui/screens/main.py
enigmatui/screens/plugboard_content_invalid_modal.py
enigmatui/screens/splash.py
enigmatui/utility/__init__.py
enigmatui/utility/observable.py
enigmatui/utility/observer.py
enigmatui/widgets/__init__.py
enigmatui/widgets/custom_header.py
enigmatui/widgets/plugboard_input.py
enigmatui/widgets/undeletable_textarea.py
enigmatui-1.2.2.dist-info/METADATA
enigmatui-1.2.2.dist-info/WHEEL
enigmatui-1.2.2.dist-info/entry_points.txt
enigmatui-1.2.2.dist-info/top_level.txt
enigmatui-1.2.2.dist-info/RECORD
