Metadata-Version: 2.4
Name: enigmatui
Version: 1.2.2
Summary: Enigma TUI is a Terminal User Interface for Enigma machines, allowing you to simulate different Enigma machine models from the terminal
Home-page: https://github.com/denismaggior8/enigma-tui
Author: Denis Maggiorotto
Requires-Dist: textual==1.0.0
Requires-Dist: enigmapython==1.3.0
Dynamic: author
Dynamic: description
Dynamic: description-content-type
Dynamic: home-page
Dynamic: requires-dist
Dynamic: summary
